variant_integrity/__init__.py
variant_integrity/__main__.py
variant_integrity/cli.py
variant_integrity/log.py
variant_integrity/utils/__init__.py
variant_integrity/utils/check_common_variant.py
variant_integrity/utils/check_high_quality.py
variant_integrity/utils/check_individuals.py
variant_integrity/utils/check_mendelian_error.py
variant_integrity/utils/get_genotypes.py
variant_integrity-0.0.4.dist-info/DESCRIPTION.rst
variant_integrity-0.0.4.dist-info/METADATA
variant_integrity-0.0.4.dist-info/RECORD
variant_integrity-0.0.4.dist-info/WHEEL
variant_integrity-0.0.4.dist-info/entry_points.txt
variant_integrity-0.0.4.dist-info/metadata.json
variant_integrity-0.0.4.dist-info/top_level.txt
